s2vit/__init__.py
s2vit/_version.py
s2vit/nn.py
s2vit/ops.py
s2vit/transformer.py
s2vit/utils.py
s2vit-0.5.1.dist-info/LICENSE
s2vit-0.5.1.dist-info/METADATA
s2vit-0.5.1.dist-info/WHEEL
s2vit-0.5.1.dist-info/top_level.txt
s2vit-0.5.1.dist-info/RECORD
