Metadata-Version: 2.1
Name: s2vit
Version: 0.5.1
Summary: Spatial Shift Vision Transformer
Author-email: Miller Wilt <miller@pyriteai.com>
Requires-Python: >=3.10
License-File: LICENSE
Requires-Dist: einops
Requires-Dist: timm
Requires-Dist: torch
Requires-Dist: torchvision
